llmdata/__init__.py
llmdata/core.py
llmdata-0.1.0.dist-info/WHEEL
llmdata-0.1.0.dist-info/METADATA
llmdata-0.1.0.dist-info/RECORD
