Metadata-Version: 2.4
Name: llmdata
Version: 0.1.0
Summary: rubrics
Keywords: rubrics,grading,eval
Author: Gavin
Author-email: Gavin <gavin@llmdata.com>
License-Expression: MIT
Classifier: Development Status :: 3 - Alpha
Classifier: Intended Audience :: Developers
Classifier: Intended Audience :: Education
Classifier: License :: OSI Approved :: MIT License
Classifier: Programming Language :: Python :: 3
Classifier: Programming Language :: Python :: 3.13
Classifier: Topic :: Education
Classifier: Topic :: Software Development :: Libraries :: Python Modules
Requires-Dist: pydantic>=2.0.0
Requires-Python: >=3.13
Project-URL: Homepage, https://github.com/The-LLM-Data-Company/rubrics/
Project-URL: Issues, https://github.com/The-LLM-Data-Company/rubrics/issues
Project-URL: Repository, https://github.com/The-LLM-Data-Company/rubrics
